cli_timer/__init__.py
cli_timer/main.py
cli_timer-1.0.3.dist-info/METADATA
cli_timer-1.0.3.dist-info/WHEEL
cli_timer-1.0.3.dist-info/entry_points.txt
cli_timer-1.0.3.dist-info/top_level.txt
cli_timer-1.0.3.dist-info/RECORD
