Metadata-Version: 2.4
Name: cli_timer
Version: 1.0.3
Requires-Dist: pynput
Requires-Dist: termcolor
Requires-Dist: pyTwistyScrambler
Dynamic: requires-dist
